<?xml version="1.0" encoding="UTF-8"?>
<objects serializationModel="Studio.02.02.00">
	<object class="MixerGroup" id="{61bd1a18-627f-4cdf-95c8-83d365798d15}">
		<property name="name">
			<value>local</value>
		</property>
		<relationship name="effectChain">
			<destination>{d7914808-3fa0-41b3-a1ae-f06571d9ed26}</destination>
		</relationship>
		<relationship name="panner">
			<destination>{ae002ca8-b328-4e92-908b-4b40713663de}</destination>
		</relationship>
		<relationship name="output">
			<destination>{057eb4b1-4d4a-4c51-81c8-4b609c1124ff}</destination>
		</relationship>
	</object>
	<object class="MixerBusEffectChain" id="{d7914808-3fa0-41b3-a1ae-f06571d9ed26}">
		<relationship name="effects">
			<destination>{6b97a144-35a7-4e55-9422-51b7f5c9b1bf}</destination>
		</relationship>
	</object>
	<object class="MixerBusPanner" id="{ae002ca8-b328-4e92-908b-4b40713663de}" />
	<object class="MixerBusFader" id="{6b97a144-35a7-4e55-9422-51b7f5c9b1bf}" />
</objects>
